[{"line":1,"elements":[{"start_timestamp":"2024-08-03T07:32:15.370Z","before":[{"result":{"duration":282802100,"status":"passed"},"match":{"location":"com.automation.steps.Hooks.setUp()"}}],"line":3,"name":"Verify user can create a user","description":"","id":"validate-the-post-request;verify-user-can-create-a-user","type":"scenario","keyword":"Scenario","steps":[{"result":{"duration":99625700,"status":"passed"},"line":4,"name":"user wants to call the \"/users\" endpoint","match":{"arguments":[{"val":"\"/users\"","offset":23}],"location":"com.automation.steps.RequestSteps.user_wants_to_call_the_endpoint(java.lang.String)"},"keyword":"Given "},{"result":{"duration":44879200,"status":"passed"},"line":5,"name":"set header \"Content-Type\" to \"application/json\"","match":{"arguments":[{"val":"\"Content-Type\"","offset":11},{"val":"\"application/json\"","offset":29}],"location":"com.automation.steps.RequestSteps.set_header_to(java.lang.String,java.lang.String)"},"keyword":"And "},{"result":{"duration":3989900,"status":"passed"},"line":6,"name":"set request body from the file \"create_user.json\"","match":{"arguments":[{"val":"\"create_user.json\"","offset":31}],"location":"com.automation.steps.RequestSteps.set_request_body_from_the_file(java.lang.String)"},"keyword":"And "},{"result":{"duration":1494281800,"status":"passed"},"line":7,"name":"user performs post call","match":{"location":"com.automation.steps.RequestSteps.user_performs_post_call()"},"keyword":"When "},{"result":{"duration":997100,"status":"passed"},"line":8,"name":"verify status code is 201","match":{"arguments":[{"val":"201","offset":22}],"location":"com.automation.steps.ResponseSteps.verify_status_code_is(int)"},"keyword":"Then "}]}],"name":"Validate the post request","description":"","id":"validate-the-post-request","keyword":"Feature","uri":"file:src/test/resources/features/create_user.feature","tags":[]},{"line":1,"elements":[{"start_timestamp":"2024-08-03T07:32:17.311Z","before":[{"result":{"status":"passed"},"match":{"location":"com.automation.steps.Hooks.setUp()"}}],"line":3,"name":"Verify user can delete a user","description":"","id":"validate-the-delete-request;verify-user-can-delete-a-user","type":"scenario","keyword":"Scenario","steps":[{"result":{"duration":35400,"status":"passed"},"line":4,"name":"user wants to call the \"/users\" endpoint","match":{"arguments":[{"val":"\"/users\"","offset":23}],"location":"com.automation.steps.RequestSteps.user_wants_to_call_the_endpoint(java.lang.String)"},"keyword":"Given "},{"result":{"status":"passed"},"line":5,"name":"set header \"Content-Type\" to \"application/json\"","match":{"arguments":[{"val":"\"Content-Type\"","offset":11},{"val":"\"application/json\"","offset":29}],"location":"com.automation.steps.RequestSteps.set_header_to(java.lang.String,java.lang.String)"},"keyword":"And "},{"result":{"status":"passed"},"line":6,"name":"set request body from the file \"create_user.json\"","match":{"arguments":[{"val":"\"create_user.json\"","offset":31}],"location":"com.automation.steps.RequestSteps.set_request_body_from_the_file(java.lang.String)"},"keyword":"And "},{"result":{"duration":581331900,"status":"passed"},"line":7,"name":"user performs post call","match":{"location":"com.automation.steps.RequestSteps.user_performs_post_call()"},"keyword":"When "},{"result":{"status":"passed"},"line":8,"name":"verify status code is 201","match":{"arguments":[{"val":"201","offset":22}],"location":"com.automation.steps.ResponseSteps.verify_status_code_is(int)"},"keyword":"Then "},{"result":{"duration":441583900,"status":"passed"},"line":9,"name":"check user id is not empty","match":{"location":"com.automation.steps.ResponseSteps.checkUserIdIsNotEmpty()"},"keyword":"And "},{"result":{"duration":11062900,"status":"passed"},"line":10,"name":"store the user id into the \"user.id\"","match":{"arguments":[{"val":"\"user.id\"","offset":27}],"location":"com.automation.steps.ResponseSteps.storeTheUserIdIntoThe(java.lang.String)"},"keyword":"And "},{"result":{"status":"passed"},"line":11,"name":"user wants to call the \"/users/@id\" endpoint","match":{"arguments":[{"val":"\"/users/@id\"","offset":23}],"location":"com.automation.steps.RequestSteps.user_wants_to_call_the_endpoint(java.lang.String)"},"keyword":"When "},{"result":{"duration":621010100,"status":"passed"},"line":12,"name":"user performs delete call","match":{"location":"com.automation.steps.RequestSteps.userPerformsDeleteCall()"},"keyword":"When "},{"result":{"duration":1073400,"status":"passed"},"line":13,"name":"verify status code is 204","match":{"arguments":[{"val":"204","offset":22}],"location":"com.automation.steps.ResponseSteps.verify_status_code_is(int)"},"keyword":"Then "}]}],"name":"Validate the delete request","description":"","id":"validate-the-delete-request","keyword":"Feature","uri":"file:src/test/resources/features/delete_user.feature","tags":[]},{"line":1,"elements":[{"start_timestamp":"2024-08-03T07:32:18.981Z","before":[{"result":{"duration":997900,"status":"passed"},"match":{"location":"com.automation.steps.Hooks.setUp()"}}],"line":3,"name":"Verify user can get a user","description":"","id":"validate-the-get-request;verify-user-can-get-a-user","type":"scenario","keyword":"Scenario","steps":[{"result":{"status":"passed"},"line":4,"name":"user wants to call the \"/users\" endpoint","match":{"arguments":[{"val":"\"/users\"","offset":23}],"location":"com.automation.steps.RequestSteps.user_wants_to_call_the_endpoint(java.lang.String)"},"keyword":"Given "},{"result":{"duration":142300,"status":"passed"},"line":5,"name":"set header \"Content-Type\" to \"application/json\"","match":{"arguments":[{"val":"\"Content-Type\"","offset":11},{"val":"\"application/json\"","offset":29}],"location":"com.automation.steps.RequestSteps.set_header_to(java.lang.String,java.lang.String)"},"keyword":"And "},{"result":{"duration":1852300,"status":"passed"},"line":6,"name":"set request body from the file \"create_user.json\"","match":{"arguments":[{"val":"\"create_user.json\"","offset":31}],"location":"com.automation.steps.RequestSteps.set_request_body_from_the_file(java.lang.String)"},"keyword":"And "},{"result":{"duration":630012600,"status":"passed"},"line":7,"name":"user performs post call","match":{"location":"com.automation.steps.RequestSteps.user_performs_post_call()"},"keyword":"When "},{"result":{"status":"passed"},"line":8,"name":"verify status code is 201","match":{"arguments":[{"val":"201","offset":22}],"location":"com.automation.steps.ResponseSteps.verify_status_code_is(int)"},"keyword":"Then "},{"result":{"duration":19940200,"status":"passed"},"line":9,"name":"check user id is not empty","match":{"location":"com.automation.steps.ResponseSteps.checkUserIdIsNotEmpty()"},"keyword":"And "},{"result":{"duration":11966900,"status":"passed"},"line":10,"name":"store the user id into the \"user.id\"","match":{"arguments":[{"val":"\"user.id\"","offset":27}],"location":"com.automation.steps.ResponseSteps.storeTheUserIdIntoThe(java.lang.String)"},"keyword":"And "},{"result":{"status":"passed"},"line":11,"name":"user wants to call the \"/users/@id\" endpoint","match":{"arguments":[{"val":"\"/users/@id\"","offset":23}],"location":"com.automation.steps.RequestSteps.user_wants_to_call_the_endpoint(java.lang.String)"},"keyword":"When "},{"result":{"duration":617868200,"status":"passed"},"line":12,"name":"user performs get call","match":{"location":"com.automation.steps.RequestSteps.userPerformsGetCall()"},"keyword":"When "},{"result":{"error_message":"java.lang.AssertionError: expected:<200> but was:<404>\r\n\tat org.junit.Assert.fail(Assert.java:88)\r\n\tat org.junit.Assert.failNotEquals(Assert.java:834)\r\n\tat org.junit.Assert.assertEquals(Assert.java:645)\r\n\tat org.junit.Assert.assertEquals(Assert.java:631)\r\n\tat com.automation.steps.ResponseSteps.verify_status_code_is(ResponseSteps.java:13)\r\n\tat ✽.verify status code is 200(file:///C:/UST_Java/TestMainRestAssured/src/test/resources/features/get_user.feature:13)\r\n","duration":2565100,"status":"failed"},"line":13,"name":"verify status code is 200","match":{"arguments":[{"val":"200","offset":22}],"location":"com.automation.steps.ResponseSteps.verify_status_code_is(int)"},"keyword":"Then "}]},{"start_timestamp":"2024-08-03T07:32:20.277Z","before":[{"result":{"duration":593300,"status":"passed"},"match":{"location":"com.automation.steps.Hooks.setUp()"}}],"line":16,"name":"Verify user can get list of user","description":"","id":"validate-the-get-request;verify-user-can-get-list-of-user","type":"scenario","keyword":"Scenario","steps":[{"result":{"status":"passed"},"line":17,"name":"user wants to call the \"/users?page=2\" endpoint","match":{"arguments":[{"val":"\"/users?page=2\"","offset":23}],"location":"com.automation.steps.RequestSteps.user_wants_to_call_the_endpoint(java.lang.String)"},"keyword":"Given "},{"result":{"duration":289678600,"status":"passed"},"line":18,"name":"user performs get call","match":{"location":"com.automation.steps.RequestSteps.userPerformsGetCall()"},"keyword":"When "},{"result":{"duration":996200,"status":"passed"},"line":19,"name":"verify status code is 200","match":{"arguments":[{"val":"200","offset":22}],"location":"com.automation.steps.ResponseSteps.verify_status_code_is(int)"},"keyword":"Then "}]}],"name":"Validate the get request","description":"","id":"validate-the-get-request","keyword":"Feature","uri":"file:src/test/resources/features/get_user.feature","tags":[]},{"line":1,"elements":[{"start_timestamp":"2024-08-03T07:32:20.571Z","before":[{"result":{"status":"passed"},"match":{"location":"com.automation.steps.Hooks.setUp()"}}],"line":13,"name":"Verify user cannot register with invalid credentials","description":"","id":"validate-register-request;verify-user-cannot-register-with-invalid-credentials;;2","type":"scenario","keyword":"Scenario Outline","steps":[{"result":{"status":"passed"},"line":5,"name":"user wants to call the \"/register\" endpoint","match":{"arguments":[{"val":"\"/register\"","offset":23}],"location":"com.automation.steps.RequestSteps.user_wants_to_call_the_endpoint(java.lang.String)"},"keyword":"Given "},{"result":{"duration":873900,"status":"passed"},"line":6,"name":"set header \"Content-Type\" to \"application/json\"","match":{"arguments":[{"val":"\"Content-Type\"","offset":11},{"val":"\"application/json\"","offset":29}],"location":"com.automation.steps.RequestSteps.set_header_to(java.lang.String,java.lang.String)"},"keyword":"And "},{"result":{"duration":232945200,"status":"passed"},"line":7,"name":"set request body from the file \"register.json\" with username \"test@yhl.com\" and password \"password\"","match":{"arguments":[{"val":"\"register.json\"","offset":31},{"val":"\"test@yhl.com\"","offset":61},{"val":"\"password\"","offset":89}],"location":"com.automation.steps.RequestSteps.setRequestBodyFromTheFileWithUsernameAndPassword(java.lang.String,java.lang.String,java.lang.String)"},"keyword":"And "},{"result":{"duration":578642300,"status":"passed"},"line":8,"name":"user performs post call","match":{"location":"com.automation.steps.RequestSteps.user_performs_post_call()"},"keyword":"When "},{"result":{"status":"passed"},"line":9,"name":"verify status code is 400","match":{"arguments":[{"val":"400","offset":22}],"location":"com.automation.steps.ResponseSteps.verify_status_code_is(int)"},"keyword":"Then "}]},{"start_timestamp":"2024-08-03T07:32:21.397Z","before":[{"result":{"duration":991900,"status":"passed"},"match":{"location":"com.automation.steps.Hooks.setUp()"}}],"line":14,"name":"Verify user cannot register with invalid credentials","description":"","id":"validate-register-request;verify-user-cannot-register-with-invalid-credentials;;3","type":"scenario","keyword":"Scenario Outline","steps":[{"result":{"status":"passed"},"line":5,"name":"user wants to call the \"/register\" endpoint","match":{"arguments":[{"val":"\"/register\"","offset":23}],"location":"com.automation.steps.RequestSteps.user_wants_to_call_the_endpoint(java.lang.String)"},"keyword":"Given "},{"result":{"duration":1001200,"status":"passed"},"line":6,"name":"set header \"Content-Type\" to \"application/json\"","match":{"arguments":[{"val":"\"Content-Type\"","offset":11},{"val":"\"application/json\"","offset":29}],"location":"com.automation.steps.RequestSteps.set_header_to(java.lang.String,java.lang.String)"},"keyword":"And "},{"result":{"duration":5986400,"status":"passed"},"line":7,"name":"set request body from the file \"register.json\" with username \"testdata@gmail.com\" and password \"password123\"","match":{"arguments":[{"val":"\"register.json\"","offset":31},{"val":"\"testdata@gmail.com\"","offset":61},{"val":"\"password123\"","offset":95}],"location":"com.automation.steps.RequestSteps.setRequestBodyFromTheFileWithUsernameAndPassword(java.lang.String,java.lang.String,java.lang.String)"},"keyword":"And "},{"result":{"duration":598604700,"status":"passed"},"line":8,"name":"user performs post call","match":{"location":"com.automation.steps.RequestSteps.user_performs_post_call()"},"keyword":"When "},{"result":{"status":"passed"},"line":9,"name":"verify status code is 400","match":{"arguments":[{"val":"400","offset":22}],"location":"com.automation.steps.ResponseSteps.verify_status_code_is(int)"},"keyword":"Then "}]},{"start_timestamp":"2024-08-03T07:32:22.008Z","before":[{"result":{"duration":880000,"status":"passed"},"match":{"location":"com.automation.steps.Hooks.setUp()"}}],"line":15,"name":"Verify user cannot register with invalid credentials","description":"","id":"validate-register-request;verify-user-cannot-register-with-invalid-credentials;;4","type":"scenario","keyword":"Scenario Outline","steps":[{"result":{"status":"passed"},"line":5,"name":"user wants to call the \"/register\" endpoint","match":{"arguments":[{"val":"\"/register\"","offset":23}],"location":"com.automation.steps.RequestSteps.user_wants_to_call_the_endpoint(java.lang.String)"},"keyword":"Given "},{"result":{"status":"passed"},"line":6,"name":"set header \"Content-Type\" to \"application/json\"","match":{"arguments":[{"val":"\"Content-Type\"","offset":11},{"val":"\"application/json\"","offset":29}],"location":"com.automation.steps.RequestSteps.set_header_to(java.lang.String,java.lang.String)"},"keyword":"And "},{"result":{"duration":3273200,"status":"passed"},"line":7,"name":"set request body from the file \"register.json\" with username \"user12@gmal.cm\" and password \"password323\"","match":{"arguments":[{"val":"\"register.json\"","offset":31},{"val":"\"user12@gmal.cm\"","offset":61},{"val":"\"password323\"","offset":91}],"location":"com.automation.steps.RequestSteps.setRequestBodyFromTheFileWithUsernameAndPassword(java.lang.String,java.lang.String,java.lang.String)"},"keyword":"And "},{"result":{"duration":611954600,"status":"passed"},"line":8,"name":"user performs post call","match":{"location":"com.automation.steps.RequestSteps.user_performs_post_call()"},"keyword":"When "},{"result":{"status":"passed"},"line":9,"name":"verify status code is 400","match":{"arguments":[{"val":"400","offset":22}],"location":"com.automation.steps.ResponseSteps.verify_status_code_is(int)"},"keyword":"Then "}]},{"start_timestamp":"2024-08-03T07:32:22.627Z","before":[{"result":{"status":"passed"},"match":{"location":"com.automation.steps.Hooks.setUp()"}}],"line":16,"name":"Verify user cannot register with invalid credentials","description":"","id":"validate-register-request;verify-user-cannot-register-with-invalid-credentials;;5","type":"scenario","keyword":"Scenario Outline","steps":[{"result":{"status":"passed"},"line":5,"name":"user wants to call the \"/register\" endpoint","match":{"arguments":[{"val":"\"/register\"","offset":23}],"location":"com.automation.steps.RequestSteps.user_wants_to_call_the_endpoint(java.lang.String)"},"keyword":"Given "},{"result":{"status":"passed"},"line":6,"name":"set header \"Content-Type\" to \"application/json\"","match":{"arguments":[{"val":"\"Content-Type\"","offset":11},{"val":"\"application/json\"","offset":29}],"location":"com.automation.steps.RequestSteps.set_header_to(java.lang.String,java.lang.String)"},"keyword":"And "},{"result":{"duration":2041900,"status":"passed"},"line":7,"name":"set request body from the file \"register.json\" with username \"test13s@yahoo.com\" and password \"Admin!23\"","match":{"arguments":[{"val":"\"register.json\"","offset":31},{"val":"\"test13s@yahoo.com\"","offset":61},{"val":"\"Admin!23\"","offset":94}],"location":"com.automation.steps.RequestSteps.setRequestBodyFromTheFileWithUsernameAndPassword(java.lang.String,java.lang.String,java.lang.String)"},"keyword":"And "},{"result":{"duration":582774800,"status":"passed"},"line":8,"name":"user performs post call","match":{"location":"com.automation.steps.RequestSteps.user_performs_post_call()"},"keyword":"When "},{"result":{"status":"passed"},"line":9,"name":"verify status code is 400","match":{"arguments":[{"val":"400","offset":22}],"location":"com.automation.steps.ResponseSteps.verify_status_code_is(int)"},"keyword":"Then "}]}],"name":"Validate register request","description":"","id":"validate-register-request","keyword":"Feature","uri":"file:src/test/resources/features/register.feature","tags":[]},{"line":1,"elements":[{"start_timestamp":"2024-08-03T07:32:23.221Z","before":[{"result":{"duration":890000,"status":"passed"},"match":{"location":"com.automation.steps.Hooks.setUp()"}}],"line":3,"name":"Verify user can update a user","description":"","id":"validate-the-update-request;verify-user-can-update-a-user","type":"scenario","keyword":"Scenario","steps":[{"result":{"status":"passed"},"line":4,"name":"user wants to call the \"/users\" endpoint","match":{"arguments":[{"val":"\"/users\"","offset":23}],"location":"com.automation.steps.RequestSteps.user_wants_to_call_the_endpoint(java.lang.String)"},"keyword":"Given "},{"result":{"status":"passed"},"line":5,"name":"set header \"Content-Type\" to \"application/json\"","match":{"arguments":[{"val":"\"Content-Type\"","offset":11},{"val":"\"application/json\"","offset":29}],"location":"com.automation.steps.RequestSteps.set_header_to(java.lang.String,java.lang.String)"},"keyword":"And "},{"result":{"duration":1523200,"status":"passed"},"line":6,"name":"set request body from the file \"create_user.json\"","match":{"arguments":[{"val":"\"create_user.json\"","offset":31}],"location":"com.automation.steps.RequestSteps.set_request_body_from_the_file(java.lang.String)"},"keyword":"And "},{"result":{"duration":619777200,"status":"passed"},"line":7,"name":"user performs post call","match":{"location":"com.automation.steps.RequestSteps.user_performs_post_call()"},"keyword":"When "},{"result":{"status":"passed"},"line":8,"name":"verify status code is 201","match":{"arguments":[{"val":"201","offset":22}],"location":"com.automation.steps.ResponseSteps.verify_status_code_is(int)"},"keyword":"Then "},{"result":{"duration":18937600,"status":"passed"},"line":9,"name":"check user id is not empty","match":{"location":"com.automation.steps.ResponseSteps.checkUserIdIsNotEmpty()"},"keyword":"And "},{"result":{"duration":10934700,"status":"passed"},"line":10,"name":"store the user id into the \"user.id\"","match":{"arguments":[{"val":"\"user.id\"","offset":27}],"location":"com.automation.steps.ResponseSteps.storeTheUserIdIntoThe(java.lang.String)"},"keyword":"And "},{"result":{"status":"passed"},"line":11,"name":"user wants to call the \"/users/@id\" endpoint","match":{"arguments":[{"val":"\"/users/@id\"","offset":23}],"location":"com.automation.steps.RequestSteps.user_wants_to_call_the_endpoint(java.lang.String)"},"keyword":"When "},{"result":{"duration":1054800,"status":"passed"},"line":12,"name":"set header \"Content-Type\" to \"application/json\"","match":{"arguments":[{"val":"\"Content-Type\"","offset":11},{"val":"\"application/json\"","offset":29}],"location":"com.automation.steps.RequestSteps.set_header_to(java.lang.String,java.lang.String)"},"keyword":"And "},{"result":{"duration":3931600,"status":"passed"},"line":13,"name":"set request body from the file \"update_user.json\" using pojo","match":{"arguments":[{"val":"\"update_user.json\"","offset":31}],"location":"com.automation.steps.RequestSteps.setRequestBodyFromTheFileUsingPojo(java.lang.String)"},"keyword":"And "},{"result":{"duration":580629000,"status":"passed"},"line":14,"name":"user performs put call","match":{"location":"com.automation.steps.RequestSteps.userPerformsPutCall()"},"keyword":"When "},{"result":{"status":"passed"},"line":15,"name":"verify status code is 200","match":{"arguments":[{"val":"200","offset":22}],"location":"com.automation.steps.ResponseSteps.verify_status_code_is(int)"},"keyword":"Then "}]}],"name":"Validate the update request","description":"","id":"validate-the-update-request","keyword":"Feature","uri":"file:src/test/resources/features/update_user.feature","tags":[]}]